runelog/__init__.py
runelog/cli.py
runelog/exceptions.py
runelog/runelog.py
runelog/runner.py
runelog-0.2.0.dist-info/METADATA
runelog-0.2.0.dist-info/WHEEL
runelog-0.2.0.dist-info/entry_points.txt
runelog-0.2.0.dist-info/RECORD
