Metadata-Version: 2.4
Name: runelog
Version: 0.2.0
Summary: A simple, file-based Python library for tracking machine learning experiments.
Project-URL: Homepage, https://github.com/gonz4lex/runelog
Project-URL: Bug Tracker, https://github.com/gonz4lex/runelog/issues
Author-email: Alex González <hello@alexgonzalezc.dev>
License: MIT
Classifier: License :: OSI Approved :: MIT License
Classifier: Operating System :: OS Independent
Classifier: Programming Language :: Python :: 3
Classifier: Topic :: Scientific/Engineering :: Artificial Intelligence
Requires-Python: >=3.10
Requires-Dist: joblib>=1.5.1
Requires-Dist: pandas>=1.5.0
Requires-Dist: pyyaml>=6.0.2
Requires-Dist: rich>=14.0.0
Requires-Dist: scikit-learn>=1.1.0
Requires-Dist: streamlit>=1.20.0
Requires-Dist: typer[all]
Provides-Extra: dev
Requires-Dist: black; extra == 'dev'
Requires-Dist: coverage; extra == 'dev'
Requires-Dist: mkdocs; extra == 'dev'
Requires-Dist: mkdocs-material; extra == 'dev'
Requires-Dist: mkdocstrings[python]; extra == 'dev'
Requires-Dist: pymdown-extensions; extra == 'dev'
Requires-Dist: pytest; extra == 'dev'
Requires-Dist: pytest-cov; extra == 'dev'
Provides-Extra: docs
Requires-Dist: mkdocs; extra == 'docs'
Requires-Dist: mkdocs-material; extra == 'docs'
Requires-Dist: mkdocstrings[python]; extra == 'docs'
Requires-Dist: pymdown-extensions; extra == 'docs'
Provides-Extra: format
Requires-Dist: black; extra == 'format'
Provides-Extra: test
Requires-Dist: coverage; extra == 'test'
Requires-Dist: pytest; extra == 'test'
Requires-Dist: pytest-cov; extra == 'test'
